tcid/__init__.py
tcid/_verification_functions.py
PyTCID-1.0.0.dist-info/LICENSE
PyTCID-1.0.0.dist-info/METADATA
PyTCID-1.0.0.dist-info/WHEEL
PyTCID-1.0.0.dist-info/top_level.txt
PyTCID-1.0.0.dist-info/RECORD
