Metadata-Version: 2.1
Name: PyTCID
Version: 1.0.0
Summary: Unofficial Python API to verify Turkish National ID Cards.
Home-page: https://github.com/ambertide/PyTCID
Author: Ege Ozkan
Author-email: egeemirozkan24@gmail.com
License: UNKNOWN
Platform: UNKNOWN
Classifier: Programming Language :: Python :: 3.6
Classifier: License :: OSI Approved :: MIT License
Classifier: Operating System :: OS Independent
Requires-Python: >=3.6
